gong_mcp/__init__.py
gong_mcp/logging_setup.py
gong_mcp/main.py
gong_mcp/py.typed
gong_mcp/settings.py
gong_mcp-0.1.1.dist-info/METADATA
gong_mcp-0.1.1.dist-info/WHEEL
gong_mcp-0.1.1.dist-info/licenses/LICENSE
gong_mcp-0.1.1.dist-info/RECORD
