Metadata-Version: 2.4
Name: gong-mcp
Version: 0.1.1
Summary: Gong MCP.
Project-URL: homepage, https://github.com/MicaelJarniac/gong-mcp
Project-URL: source, https://github.com/MicaelJarniac/gong-mcp
Project-URL: download, https://pypi.org/project/gong-mcp/#files
Project-URL: changelog, https://github.com/MicaelJarniac/gong-mcp/blob/main/docs/CHANGELOG.md
Project-URL: documentation, https://gong-mcp.readthedocs.io
Project-URL: issues, https://github.com/MicaelJarniac/gong-mcp/issues
Author-email: Micael Jarniac <micael@jarniac.dev>
License: MIT
License-File: LICENSE
Classifier: Development Status :: 1 - Planning
Classifier: License :: OSI Approved :: MIT License
Classifier: Natural Language :: English
Classifier: Operating System :: OS Independent
Classifier: Programming Language :: Python :: 3
Classifier: Typing :: Typed
Requires-Python: >=3.13
Requires-Dist: gongy>=0.5.3
Requires-Dist: logfire[aiohttp-client]>=4.3.3
Requires-Dist: loguru>=0.7.3
Requires-Dist: mcp[cli]>=1.12.4
Requires-Dist: pydantic-ai>=0.7.0
Requires-Dist: pydantic-settings>=2.10.1
Requires-Dist: pydantic>=2.11.7
Requires-Dist: typer>=0.16.0
